flask_ngrok/__init__.py
flask_ngrok/flask_ngrok.py
nlpbook/__init__.py
nlpbook/arguments.py
nlpbook/data_utils.py
nlpbook/factory.py
nlpbook/metrics.py
nlpbook/utils.py
nlpbook/cls/__init__.py
nlpbook/cls/cli.py
nlpbook/cls/corpus.py
nlpbook/cls/task.py
nlpbook/dp/__init__.py
nlpbook/dp/cli.py
nlpbook/dp/corpus.py
nlpbook/dp/model.py
nlpbook/dp/task.py
nlpbook/generation/__init__.py
nlpbook/generation/arguments.py
nlpbook/generation/corpus.py
nlpbook/generation/deploy.py
nlpbook/generation/task.py
nlpbook/ner/__init__.py
nlpbook/ner/cli.py
nlpbook/ner/corpus.py
nlpbook/ner/task.py
nlpbook/paircls/__init__.py
nlpbook/paircls/corpus.py
nlpbook/paircls/deploy.py
nlpbook/qa/__init__.py
nlpbook/qa/arguments.py
nlpbook/qa/corpus.py
nlpbook/qa/deploy.py
nlpbook/qa/task.py
chrislab-0.7.1.dist-info/LICENSE
chrislab-0.7.1.dist-info/METADATA
chrislab-0.7.1.dist-info/WHEEL
chrislab-0.7.1.dist-info/entry_points.txt
chrislab-0.7.1.dist-info/top_level.txt
chrislab-0.7.1.dist-info/zip-safe
chrislab-0.7.1.dist-info/RECORD
