Metadata-Version: 2.1
Name: chrislab
Version: 0.7.1
Summary: An advanced tool for doing experimental study.
Home-page: https://github.com/chrisjihee/chrislab
Author: Jihee Ryu
Author-email: chrisjihee@naver.com
License: MIT License
Classifier: Development Status :: 3 - Alpha
Classifier: License :: OSI Approved :: MIT License
Classifier: Programming Language :: Python :: 3
Classifier: Programming Language :: Python :: 3.9
Classifier: Programming Language :: Python :: 3.10
Classifier: Programming Language :: Python :: 3.11
License-File: LICENSE
Requires-Dist: chrisbase
Requires-Dist: Korpora
Requires-Dist: Flask
Requires-Dist: Flask-Cors
